stochastipy/__init__.py
stochastipy-0.1.0.dist-info/LICENSE
stochastipy-0.1.0.dist-info/METADATA
stochastipy-0.1.0.dist-info/WHEEL
stochastipy-0.1.0.dist-info/top_level.txt
stochastipy-0.1.0.dist-info/RECORD
